quat_to_euler/__init__.py
quat_to_euler-2018.11.20.dist-info/LICENSE
quat_to_euler-2018.11.20.dist-info/METADATA
quat_to_euler-2018.11.20.dist-info/WHEEL
quat_to_euler-2018.11.20.dist-info/top_level.txt
quat_to_euler-2018.11.20.dist-info/RECORD
