Metadata-Version: 2.1
Name: quat-to-euler
Version: 2018.11.20
Summary: Adds a quaternion to Euler Unity-like convention method to NumPy
Home-page: https://github.com/javigonzalo/quat_to_euler
Author: Javier Gonzalez Alonso
Author-email: javigonzauva@gmail.com
License: UNKNOWN
Platform: UNKNOWN
Classifier: Programming Language :: Python :: 3
Classifier: License :: OSI Approved :: MIT License
Classifier: Operating System :: OS Independent
